fastapi_scheduler/__init__.py
fastapi_scheduler/admin.py
fastapi_scheduler/locale/base.pot
fastapi_scheduler/locale/zh_CN/LC_MESSAGES/messages.mo
fastapi_scheduler/locale/zh_CN/LC_MESSAGES/messages.po
fastapi_scheduler-0.0.15.dist-info/WHEEL
fastapi_scheduler-0.0.15.dist-info/METADATA
fastapi_scheduler-0.0.15.dist-info/RECORD
