Metadata-Version: 2.1
Name: fastapi_scheduler
Version: 0.0.15
Summary: FastAPI-Scheduler is a simple scheduled task management FastAPI extension based on APScheduler.
Keywords: FastAPI-Amis-Admin,FastAPI-APScheduler,fastapi-scheduler,APScheduler
Author-email: Atomi <1456417373@qq.com>
Maintainer-email: Atomi <1456417373@qq.com>
Requires-Python: >=3.7
Classifier: Framework :: FastAPI
Classifier: Environment :: Web Environment
Classifier: Topic :: System :: Systems Administration
Classifier: License :: OSI Approved :: Apache Software License
Classifier: Operating System :: OS Independent
Classifier: Programming Language :: Python :: 3
Classifier: Programming Language :: Python :: 3.7
Classifier: Programming Language :: Python :: 3.8
Classifier: Programming Language :: Python :: 3.9
Classifier: Programming Language :: Python :: 3.10
Requires-Dist: fastapi-amis-admin>=0.6.0,<0.8.0
Requires-Dist: APScheduler>=3.8.0
Requires-Dist: pytest >=6.2.4,<7.0.0 ; extra == "test"
Project-URL: FastAPI-Amis-Admin, https://github.com/amisadmin/fastapi_amis_admin
Project-URL: Source, https://github.com/amisadmin/fastapi_scheduler
Provides-Extra: test
